NeuroSurgeon/__init__.py
NeuroSurgeon/Masking/__init__.py
NeuroSurgeon/Masking/contsparse_layer.py
NeuroSurgeon/Masking/hardconcrete_layer.py
NeuroSurgeon/Masking/magprune_layer.py
NeuroSurgeon/Masking/mask_layer.py
NeuroSurgeon/Masking/test/__init__.py
NeuroSurgeon/Masking/test/test_contsparse.py
NeuroSurgeon/Masking/test/test_hardconcrete.py
NeuroSurgeon/Masking/test/test_magprune.py
NeuroSurgeon/Models/__init__.py
NeuroSurgeon/Models/circuit_model.py
NeuroSurgeon/Models/model_configs.py
NeuroSurgeon/Models/test/__init__.py
NeuroSurgeon/Models/test/test_circuit_model_bert.py
NeuroSurgeon/Models/test/test_other_models.py
NeuroSurgeon/Probing/__init__.py
NeuroSurgeon/Probing/probe_configs.py
NeuroSurgeon/Probing/residual_update_model.py
NeuroSurgeon/Probing/subnetwork_probe.py
NeuroSurgeon/Probing/test/__init__.py
NeuroSurgeon/Probing/test/test_residual_update_model.py
NeuroSurgeon/Probing/test/test_subnetwork_probe.py
NeuroSurgeon/Visualization/__init__.py
NeuroSurgeon/Visualization/visualizer.py
NeuroSurgeon/Visualization/test/__init__.py
NeuroSurgeon/Visualization/test/test_visualizer.py
NeuroSurgeon-0.1.0.dist-info/LICENSE
NeuroSurgeon-0.1.0.dist-info/METADATA
NeuroSurgeon-0.1.0.dist-info/WHEEL
NeuroSurgeon-0.1.0.dist-info/top_level.txt
NeuroSurgeon-0.1.0.dist-info/RECORD
