Metadata-Version: 2.1
Name: NeuroSurgeon
Version: 0.1.0
Summary: A toolkit for subnetwork analysis
Home-page: https://github.com/mlepori1/NeuroSurgeon
Author: Michael Lepori
Author-email: michael_lepori@brown.edu
License: MIT
Classifier: Intended Audience :: Science/Research
Classifier: License :: OSI Approved :: MIT License
Classifier: Operating System :: POSIX :: Linux
Classifier: Programming Language :: Python :: 3.9
License-File: LICENSE
Requires-Dist: torch (>=2.0.1)
Requires-Dist: transformers
Requires-Dist: matplotlib
Provides-Extra: tests
Requires-Dist: pytest ; extra == 'tests'
Requires-Dist: datasets ; extra == 'tests'
